purifai/__init__.py
purifai/methodSelection.py
purifAI-0.1.3.dist-info/METADATA
purifAI-0.1.3.dist-info/WHEEL
purifAI-0.1.3.dist-info/top_level.txt
purifAI-0.1.3.dist-info/RECORD
